blackout_regex.py
alerta_blackout_regex-3.1.0.dist-info/LICENSE
alerta_blackout_regex-3.1.0.dist-info/METADATA
alerta_blackout_regex-3.1.0.dist-info/WHEEL
alerta_blackout_regex-3.1.0.dist-info/entry_points.txt
alerta_blackout_regex-3.1.0.dist-info/top_level.txt
alerta_blackout_regex-3.1.0.dist-info/zip-safe
alerta_blackout_regex-3.1.0.dist-info/RECORD
