Metadata-Version: 2.1
Name: alerta-blackout-regex
Version: 3.1.0
Summary: Alerta Blackout enhancement plugin
Home-page: https://github.com/mirceaulinic/alerta-blackout-regex
Author: Mircea Ulinic
Author-email: ping@mirceaulinic.net
License: Apache License 2.0
License-File: LICENSE
